wandb_mv/__init__.py
wandb_mv/utils.py
wandb_mv/versioner.py
wandb_mv-0.2.6.dist-info/LICENSE
wandb_mv-0.2.6.dist-info/METADATA
wandb_mv-0.2.6.dist-info/WHEEL
wandb_mv-0.2.6.dist-info/top_level.txt
wandb_mv-0.2.6.dist-info/RECORD
