Metadata-Version: 2.1
Name: wandb-mv
Version: 0.2.6
Summary: Model Versioning using Weight & Biases
Home-page: https://github.com/hectorLop/Wandb-MV
Author: Hector Lopez
Author-email: lopez.almazan.hector@gmail.com
License: MIT
Platform: UNKNOWN
License-File: LICENSE
Requires-Dist: wandb
